lse_indexing_pipeline/__init__.py
lse_indexing_pipeline/convert_pdf_to_png.py
lse_indexing_pipeline/utils.py
lse_indexing_pipeline-0.1.2.dist-info/licenses/LICENSE
lse_indexing_pipeline-0.1.2.dist-info/METADATA
lse_indexing_pipeline-0.1.2.dist-info/WHEEL
lse_indexing_pipeline-0.1.2.dist-info/top_level.txt
lse_indexing_pipeline-0.1.2.dist-info/RECORD
