Metadata-Version: 2.4
Name: lse-indexing-pipeline
Version: 0.1.2
Summary: Generate vectorstore for RAG systems using an automated indexing pipeline
License: MIT License
Requires-Python: >=3.11
License-File: LICENSE
Requires-Dist: pymupdf
Requires-Dist: tqdm
Dynamic: license-file
